[
  {
    "x": 1,
    "value_mwh": 0.0
  },
  {
    "x": 2,
    "value_mwh": 0.0
  },
  {
    "x": 3,
    "value_mwh": 0.0
  },
  {
    "x": 4,
    "value_mwh": 0.0
  },
  {
    "x": 5,
    "value_mwh": 6e-06
  },
  {
    "x": 6,
    "value_mwh": 0.081894
  },
  {
    "x": 7,
    "value_mwh": 0.178278
  },
  {
    "x": 8,
    "value_mwh": 0.241002
  },
  {
    "x": 9,
    "value_mwh": 0.327027
  },
  {
    "x": 10,
    "value_mwh": 0.392479
  },
  {
    "x": 11,
    "value_mwh": 0.440523
  },
  {
    "x": 12,
    "value_mwh": 0.46832
  },
  {
    "x": 13,
    "value_mwh": 0.462858
  },
  {
    "x": 14,
    "value_mwh": 0.43171
  },
  {
    "x": 15,
    "value_mwh": 0.378926
  },
  {
    "x": 16,
    "value_mwh": 0.306818
  },
  {
    "x": 17,
    "value_mwh": 0.236789
  },
  {
    "x": 18,
    "value_mwh": 0.165127
  },
  {
    "x": 19,
    "value_mwh": 0.083976
  },
  {
    "x": 20,
    "value_mwh": 0.0
  },
  {
    "x": 21,
    "value_mwh": 0.0
  },
  {
    "x": 22,
    "value_mwh": 0.0
  },
  {
    "x": 23,
    "value_mwh": 0.0
  },
  {
    "x": 24,
    "value_mwh": 0.0
  }
]