[
  {
    "x": 1,
    "value_mwh": 0.0
  },
  {
    "x": 2,
    "value_mwh": 0.0
  },
  {
    "x": 3,
    "value_mwh": 0.0
  },
  {
    "x": 4,
    "value_mwh": 0.0
  },
  {
    "x": 5,
    "value_mwh": 0.0
  },
  {
    "x": 6,
    "value_mwh": 0.0
  },
  {
    "x": 7,
    "value_mwh": 0.000198
  },
  {
    "x": 8,
    "value_mwh": 0.006005
  },
  {
    "x": 9,
    "value_mwh": 0.008374
  },
  {
    "x": 10,
    "value_mwh": 0.013016
  },
  {
    "x": 11,
    "value_mwh": 0.014369
  },
  {
    "x": 12,
    "value_mwh": 0.018165
  },
  {
    "x": 13,
    "value_mwh": 0.01707
  },
  {
    "x": 14,
    "value_mwh": 0.013834
  },
  {
    "x": 15,
    "value_mwh": 0.010355
  },
  {
    "x": 16,
    "value_mwh": 0.005241
  },
  {
    "x": 17,
    "value_mwh": 0.000636
  },
  {
    "x": 18,
    "value_mwh": 0.0
  },
  {
    "x": 19,
    "value_mwh": 0.0
  },
  {
    "x": 20,
    "value_mwh": 0.0
  },
  {
    "x": 21,
    "value_mwh": 0.0
  },
  {
    "x": 22,
    "value_mwh": 0.0
  },
  {
    "x": 23,
    "value_mwh": 0.0
  },
  {
    "x": 24,
    "value_mwh": 0.0
  }
]