[
  {
    "value_mwh": 12581.961169811879,
    "x": 1
  },
  {
    "value_mwh": 12581.961169811879,
    "x": 2
  },
  {
    "value_mwh": 12581.961169811879,
    "x": 3
  },
  {
    "value_mwh": 12581.961169811879,
    "x": 4
  },
  {
    "value_mwh": 12581.961169811879,
    "x": 5
  },
  {
    "value_mwh": 12581.961169811879,
    "x": 6
  },
  {
    "value_mwh": 12803.415075435872,
    "x": 7
  },
  {
    "value_mwh": 13143.125953962695,
    "x": 8
  },
  {
    "value_mwh": 13573.72144823765,
    "x": 9
  },
  {
    "value_mwh": 13623.746790623823,
    "x": 10
  },
  {
    "value_mwh": 13888.576967968827,
    "x": 11
  },
  {
    "value_mwh": 14526.615077002381,
    "x": 12
  },
  {
    "value_mwh": 14483.679279994205,
    "x": 13
  },
  {
    "value_mwh": 14312.9219163188,
    "x": 14
  },
  {
    "value_mwh": 13934.868762789072,
    "x": 15
  },
  {
    "value_mwh": 13493.219450720611,
    "x": 16
  },
  {
    "value_mwh": 12991.68655269302,
    "x": 17
  },
  {
    "value_mwh": 12626.176440985906,
    "x": 18
  },
  {
    "value_mwh": 12581.961169811879,
    "x": 19
  },
  {
    "value_mwh": 12581.961169811879,
    "x": 20
  },
  {
    "value_mwh": 12581.961169811879,
    "x": 21
  },
  {
    "value_mwh": 12581.961169811879,
    "x": 22
  },
  {
    "value_mwh": 12581.961169811879,
    "x": 23
  },
  {
    "value_mwh": 12581.961169811879,
    "x": 24
  }
]