[
  {
    "value_mwh": 0.0,
    "x": 1
  },
  {
    "value_mwh": 0.0,
    "x": 2
  },
  {
    "value_mwh": 0.0,
    "x": 3
  },
  {
    "value_mwh": 0.0,
    "x": 4
  },
  {
    "value_mwh": 0.0,
    "x": 5
  },
  {
    "value_mwh": 70.31791367273584,
    "x": 6
  },
  {
    "value_mwh": 1758.8351341044875,
    "x": 7
  },
  {
    "value_mwh": 4504.782936485551,
    "x": 8
  },
  {
    "value_mwh": 4052.5966051862697,
    "x": 9
  },
  {
    "value_mwh": 4852.601512633341,
    "x": 10
  },
  {
    "value_mwh": 8985.608981246636,
    "x": 11
  },
  {
    "value_mwh": 9042.950245235286,
    "x": 12
  },
  {
    "value_mwh": 10559.332762165324,
    "x": 13
  },
  {
    "value_mwh": 9678.695168219705,
    "x": 14
  },
  {
    "value_mwh": 4630.223883431709,
    "x": 15
  },
  {
    "value_mwh": 3723.632990117919,
    "x": 16
  },
  {
    "value_mwh": 3064.263910016318,
    "x": 17
  },
  {
    "value_mwh": 83.96003257138965,
    "x": 18
  },
  {
    "value_mwh": 0.0,
    "x": 19
  },
  {
    "value_mwh": 0.0,
    "x": 20
  },
  {
    "value_mwh": 0.0,
    "x": 21
  },
  {
    "value_mwh": 0.0,
    "x": 22
  },
  {
    "value_mwh": 0.0,
    "x": 23
  },
  {
    "value_mwh": 0.0,
    "x": 24
  }
]