[
  {
    "base_group": null,
    "category_code": "cons_domestic",
    "domain": "consumption",
    "mun_cod": null,
    "name": "Oristano",
    "prov_cod": 95,
    "reg_cod": 20,
    "territory_id": 7902,
    "value_mwh": 12817859.4193442
  },
  {
    "base_group": null,
    "category_code": "cons_domestic",
    "domain": "consumption",
    "mun_cod": null,
    "name": "Viterbo",
    "prov_cod": 56,
    "reg_cod": 12,
    "territory_id": 7903,
    "value_mwh": 21701974.664368
  },
  {
    "base_group": null,
    "category_code": "cons_domestic",
    "domain": "consumption",
    "mun_cod": null,
    "name": "Savona",
    "prov_cod": 9,
    "reg_cod": 7,
    "territory_id": 7904,
    "value_mwh": 20833804.4271596
  },
  {
    "base_group": null,
    "category_code": "cons_domestic",
    "domain": "consumption",
    "mun_cod": null,
    "name": "Lodi",
    "prov_cod": 98,
    "reg_cod": 3,
    "territory_id": 7905,
    "value_mwh": 15464399.9346436
  },
  {
    "base_group": null,
    "category_code": "cons_domestic",
    "domain": "consumption",
    "mun_cod": null,
    "name": "Prato",
    "prov_cod": 100,
    "reg_cod": 9,
    "territory_id": 7906,
    "value_mwh": 17056165.27279
  },
  {
    "base_group": null,
    "category_code": "cons_domestic",
    "domain": "consumption",
    "mun_cod": null,
    "name": "Pescara",
    "prov_cod": 68,
    "reg_cod": 13,
    "territory_id": 7907,
    "value_mwh": 20305765.639247
  },
  {
    "base_group": null,
    "category_code": "cons_domestic",
    "domain": "consumption",
    "mun_cod": null,
    "name": "Arezzo",
    "prov_cod": 51,
    "reg_cod": 9,
    "territory_id": 7908,
    "value_mwh": 23004076.737468
  },
  {
    "base_group": null,
    "category_code": "cons_domestic",
    "domain": "consumption",
    "mun_cod": null,
    "name": "Como",
    "prov_cod": 13,
    "reg_cod": 3,
    "territory_id": 7909,
    "value_mwh": 42368485.339354
  },
  {
    "base_group": null,
    "category_code": "cons_domestic",
    "domain": "consumption",
    "mun_cod": null,
    "name": "Lecco",
    "prov_cod": 97,
    "reg_cod": 3,
    "territory_id": 7910,
    "value_mwh": 22791698.2853762
  },
  {
    "base_group": null,
    "category_code": "cons_domestic",
    "domain": "consumption",
    "mun_cod": null,
    "name": "Verona",
    "prov_cod": 23,
    "reg_cod": 5,
    "territory_id": 7911,
    "value_mwh": 68509028.547579
  },
  {
    "base_group": null,
    "category_code": "cons_domestic",
    "domain": "consumption",
    "mun_cod": null,
    "name": "Pistoia",
    "prov_cod": 47,
    "reg_cod": 9,
    "territory_id": 7912,
    "value_mwh": 20452606.7868
  },
  {
    "base_group": null,
    "category_code": "cons_domestic",
    "domain": "consumption",
    "mun_cod": null,
    "name": "Ascoli Piceno",
    "prov_cod": 44,
    "reg_cod": 11,
    "territory_id": 7913,
    "value_mwh": 13124072.448834
  },
  {
    "base_group": null,
    "category_code": "cons_domestic",
    "domain": "consumption",
    "mun_cod": null,
    "name": "Ancona",
    "prov_cod": 42,
    "reg_cod": 11,
    "territory_id": 7914,
    "value_mwh": 29255945.034225
  },
  {
    "base_group": null,
    "category_code": "cons_domestic",
    "domain": "consumption",
    "mun_cod": null,
    "name": "L'Aquila",
    "prov_cod": 66,
    "reg_cod": 13,
    "territory_id": 7915,
    "value_mwh": 18723056.9613313
  },
  {
    "base_group": null,
    "category_code": "cons_domestic",
    "domain": "consumption",
    "mun_cod": null,
    "name": "Imperia",
    "prov_cod": 8,
    "reg_cod": 7,
    "territory_id": 7916,
    "value_mwh": 16626693.4021875
  },
  {
    "base_group": null,
    "category_code": "cons_domestic",
    "domain": "consumption",
    "mun_cod": null,
    "name": "Caltanissetta",
    "prov_cod": 85,
    "reg_cod": 19,
    "territory_id": 7917,
    "value_mwh": 17180819.147693
  },
  {
    "base_group": null,
    "category_code": "cons_domestic",
    "domain": "consumption",
    "mun_cod": null,
    "name": "Salerno",
    "prov_cod": 65,
    "reg_cod": 15,
    "territory_id": 7918,
    "value_mwh": 67010651.017519
  },
  {
    "base_group": null,
    "category_code": "cons_domestic",
    "domain": "consumption",
    "mun_cod": null,
    "name": "Torino",
    "prov_cod": 1,
    "reg_cod": 1,
    "territory_id": 7919,
    "value_mwh": 147300423.455221
  },
  {
    "base_group": null,
    "category_code": "cons_domestic",
    "domain": "consumption",
    "mun_cod": null,
    "name": "Monza e della Brianza",
    "prov_cod": 108,
    "reg_cod": 3,
    "territory_id": 7920,
    "value_mwh": 60350567.04733
  },
  {
    "base_group": null,
    "category_code": "cons_domestic",
    "domain": "consumption",
    "mun_cod": null,
    "name": "Bari",
    "prov_cod": 72,
    "reg_cod": 16,
    "territory_id": 7921,
    "value_mwh": 82969372.791711
  },
  {
    "base_group": null,
    "category_code": "cons_domestic",
    "domain": "consumption",
    "mun_cod": null,
    "name": "Benevento",
    "prov_cod": 62,
    "reg_cod": 15,
    "territory_id": 7922,
    "value_mwh": 16034117.276972
  },
  {
    "base_group": null,
    "category_code": "cons_domestic",
    "domain": "consumption",
    "mun_cod": null,
    "name": "Treviso",
    "prov_cod": 26,
    "reg_cod": 5,
    "territory_id": 7923,
    "value_mwh": 64697508.482108
  },
  {
    "base_group": null,
    "category_code": "cons_domestic",
    "domain": "consumption",
    "mun_cod": null,
    "name": "Brindisi",
    "prov_cod": 74,
    "reg_cod": 16,
    "territory_id": 7924,
    "value_mwh": 29489214.50308
  },
  {
    "base_group": null,
    "category_code": "cons_domestic",
    "domain": "consumption",
    "mun_cod": null,
    "name": "Bologna",
    "prov_cod": 37,
    "reg_cod": 8,
    "territory_id": 7925,
    "value_mwh": 70966240.411624
  },
  {
    "base_group": null,
    "category_code": "cons_domestic",
    "domain": "consumption",
    "mun_cod": null,
    "name": "Cagliari",
    "prov_cod": 92,
    "reg_cod": 20,
    "territory_id": 7926,
    "value_mwh": 30830117.986929
  },
  {
    "base_group": null,
    "category_code": "cons_domestic",
    "domain": "consumption",
    "mun_cod": null,
    "name": "Trieste",
    "prov_cod": 32,
    "reg_cod": 6,
    "territory_id": 7927,
    "value_mwh": 15565470.110826
  },
  {
    "base_group": null,
    "category_code": "cons_domestic",
    "domain": "consumption",
    "mun_cod": null,
    "name": "Nuoro",
    "prov_cod": 91,
    "reg_cod": 20,
    "territory_id": 7928,
    "value_mwh": 16611955.757146
  },
  {
    "base_group": null,
    "category_code": "cons_domestic",
    "domain": "consumption",
    "mun_cod": null,
    "name": "Rimini",
    "prov_cod": 99,
    "reg_cod": 8,
    "territory_id": 7929,
    "value_mwh": 26257442.237582
  },
  {
    "base_group": null,
    "category_code": "cons_domestic",
    "domain": "consumption",
    "mun_cod": null,
    "name": "Catanzaro",
    "prov_cod": 79,
    "reg_cod": 18,
    "territory_id": 7930,
    "value_mwh": 23714956.773521
  },
  {
    "base_group": null,
    "category_code": "cons_domestic",
    "domain": "consumption",
    "mun_cod": null,
    "name": "Bolzano",
    "prov_cod": 21,
    "reg_cod": 4,
    "territory_id": 7931,
    "value_mwh": 32963234.3644125
  },
  {
    "base_group": null,
    "category_code": "cons_domestic",
    "domain": "consumption",
    "mun_cod": null,
    "name": "Asti",
    "prov_cod": 5,
    "reg_cod": 1,
    "territory_id": 7932,
    "value_mwh": 15157434.6811514
  },
  {
    "base_group": null,
    "category_code": "cons_domestic",
    "domain": "consumption",
    "mun_cod": null,
    "name": "Potenza",
    "prov_cod": 76,
    "reg_cod": 17,
    "territory_id": 7933,
    "value_mwh": 19637416.566734
  },
  {
    "base_group": null,
    "category_code": "cons_domestic",
    "domain": "consumption",
    "mun_cod": null,
    "name": "Sassari",
    "prov_cod": 90,
    "reg_cod": 20,
    "territory_id": 7934,
    "value_mwh": 49062261.9975259
  },
  {
    "base_group": null,
    "category_code": "cons_domestic",
    "domain": "consumption",
    "mun_cod": null,
    "name": "Cremona",
    "prov_cod": 19,
    "reg_cod": 3,
    "territory_id": 7935,
    "value_mwh": 25840126.610811
  },
  {
    "base_group": null,
    "category_code": "cons_domestic",
    "domain": "consumption",
    "mun_cod": null,
    "name": "Biella",
    "prov_cod": 96,
    "reg_cod": 1,
    "territory_id": 7936,
    "value_mwh": 11975993.3273018
  },
  {
    "base_group": null,
    "category_code": "cons_domestic",
    "domain": "consumption",
    "mun_cod": null,
    "name": "Frosinone",
    "prov_cod": 60,
    "reg_cod": 12,
    "territory_id": 7937,
    "value_mwh": 32713545.8192
  },
  {
    "base_group": null,
    "category_code": "cons_domestic",
    "domain": "consumption",
    "mun_cod": null,
    "name": "Caserta",
    "prov_cod": 61,
    "reg_cod": 15,
    "territory_id": 7938,
    "value_mwh": 60860832.185772
  },
  {
    "base_group": null,
    "category_code": "cons_domestic",
    "domain": "consumption",
    "mun_cod": null,
    "name": "Terni",
    "prov_cod": 55,
    "reg_cod": 10,
    "territory_id": 7939,
    "value_mwh": 14508660.2791335
  },
  {
    "base_group": null,
    "category_code": "cons_domestic",
    "domain": "consumption",
    "mun_cod": null,
    "name": "Palermo",
    "prov_cod": 82,
    "reg_cod": 19,
    "territory_id": 7940,
    "value_mwh": 96262073.617016
  },
  {
    "base_group": null,
    "category_code": "cons_domestic",
    "domain": "consumption",
    "mun_cod": null,
    "name": "Modena",
    "prov_cod": 36,
    "reg_cod": 8,
    "territory_id": 7941,
    "value_mwh": 53660994.201849
  },
  {
    "base_group": null,
    "category_code": "cons_domestic",
    "domain": "consumption",
    "mun_cod": null,
    "name": "Pisa",
    "prov_cod": 50,
    "reg_cod": 9,
    "territory_id": 7942,
    "value_mwh": 29482462.681816
  },
  {
    "base_group": null,
    "category_code": "cons_domestic",
    "domain": "consumption",
    "mun_cod": null,
    "name": "Pavia",
    "prov_cod": 18,
    "reg_cod": 3,
    "territory_id": 7943,
    "value_mwh": 39004600.6427652
  },
  {
    "base_group": null,
    "category_code": "cons_domestic",
    "domain": "consumption",
    "mun_cod": null,
    "name": "Reggio di Calabria",
    "prov_cod": 80,
    "reg_cod": 18,
    "territory_id": 7944,
    "value_mwh": 38889964.914434
  },
  {
    "base_group": null,
    "category_code": "cons_domestic",
    "domain": "consumption",
    "mun_cod": null,
    "name": "Chieti",
    "prov_cod": 69,
    "reg_cod": 13,
    "territory_id": 7945,
    "value_mwh": 24106123.2030385
  },
  {
    "base_group": null,
    "category_code": "cons_domestic",
    "domain": "consumption",
    "mun_cod": null,
    "name": "Forli'-Cesena",
    "prov_cod": 40,
    "reg_cod": 8,
    "territory_id": 7946,
    "value_mwh": 26676409.79312
  },
  {
    "base_group": null,
    "category_code": "cons_domestic",
    "domain": "consumption",
    "mun_cod": null,
    "name": "Lecce",
    "prov_cod": 75,
    "reg_cod": 16,
    "territory_id": 7947,
    "value_mwh": 59720303.445133
  },
  {
    "base_group": null,
    "category_code": "cons_domestic",
    "domain": "consumption",
    "mun_cod": null,
    "name": "Vercelli",
    "prov_cod": 2,
    "reg_cod": 1,
    "territory_id": 7948,
    "value_mwh": 11502677.2443521
  },
  {
    "base_group": null,
    "category_code": "cons_domestic",
    "domain": "consumption",
    "mun_cod": null,
    "name": "Pesaro e Urbino",
    "prov_cod": 41,
    "reg_cod": 11,
    "territory_id": 7949,
    "value_mwh": 22860035.786969
  },
  {
    "base_group": null,
    "category_code": "cons_domestic",
    "domain": "consumption",
    "mun_cod": null,
    "name": "Messina",
    "prov_cod": 83,
    "reg_cod": 19,
    "territory_id": 7950,
    "value_mwh": 47762853.3064745
  },
  {
    "base_group": null,
    "category_code": "cons_domestic",
    "domain": "consumption",
    "mun_cod": null,
    "name": "Macerata",
    "prov_cod": 43,
    "reg_cod": 11,
    "territory_id": 7951,
    "value_mwh": 20185524.5780355
  },
  {
    "base_group": null,
    "category_code": "cons_domestic",
    "domain": "consumption",
    "mun_cod": null,
    "name": "Alessandria",
    "prov_cod": 6,
    "reg_cod": 1,
    "territory_id": 7952,
    "value_mwh": 28924279.8188929
  },
  {
    "base_group": null,
    "category_code": "cons_domestic",
    "domain": "consumption",
    "mun_cod": null,
    "name": "Pordenone",
    "prov_cod": 93,
    "reg_cod": 6,
    "territory_id": 7953,
    "value_mwh": 22830091.35813
  },
  {
    "base_group": null,
    "category_code": "cons_domestic",
    "domain": "consumption",
    "mun_cod": null,
    "name": "Roma",
    "prov_cod": 58,
    "reg_cod": 12,
    "territory_id": 7954,
    "value_mwh": 311765298.94025
  },
  {
    "base_group": null,
    "category_code": "cons_domestic",
    "domain": "consumption",
    "mun_cod": null,
    "name": "Rieti",
    "prov_cod": 57,
    "reg_cod": 12,
    "territory_id": 7955,
    "value_mwh": 10561187.4267553
  },
  {
    "base_group": null,
    "category_code": "cons_domestic",
    "domain": "consumption",
    "mun_cod": null,
    "name": "Siracusa",
    "prov_cod": 89,
    "reg_cod": 19,
    "territory_id": 7956,
    "value_mwh": 33466759.677699
  },
  {
    "base_group": null,
    "category_code": "cons_domestic",
    "domain": "consumption",
    "mun_cod": null,
    "name": "Siena",
    "prov_cod": 52,
    "reg_cod": 9,
    "territory_id": 7957,
    "value_mwh": 18750785.437718
  },
  {
    "base_group": null,
    "category_code": "cons_domestic",
    "domain": "consumption",
    "mun_cod": null,
    "name": "Venezia",
    "prov_cod": 27,
    "reg_cod": 5,
    "territory_id": 7958,
    "value_mwh": 64811191.34674
  },
  {
    "base_group": null,
    "category_code": "cons_domestic",
    "domain": "consumption",
    "mun_cod": null,
    "name": "Fermo",
    "prov_cod": 109,
    "reg_cod": 11,
    "territory_id": 7959,
    "value_mwh": 11029418.529564
  },
  {
    "base_group": null,
    "category_code": "cons_domestic",
    "domain": "consumption",
    "mun_cod": null,
    "name": "Avellino",
    "prov_cod": 64,
    "reg_cod": 15,
    "territory_id": 7960,
    "value_mwh": 22758038.002153
  },
  {
    "base_group": null,
    "category_code": "cons_domestic",
    "domain": "consumption",
    "mun_cod": null,
    "name": "Napoli",
    "prov_cod": 63,
    "reg_cod": 15,
    "territory_id": 7961,
    "value_mwh": 187295276.310709
  },
  {
    "base_group": null,
    "category_code": "cons_domestic",
    "domain": "consumption",
    "mun_cod": null,
    "name": "Crotone",
    "prov_cod": 101,
    "reg_cod": 18,
    "territory_id": 7962,
    "value_mwh": 11993656.829375
  },
  {
    "base_group": null,
    "category_code": "cons_domestic",
    "domain": "consumption",
    "mun_cod": null,
    "name": "Campobasso",
    "prov_cod": 70,
    "reg_cod": 14,
    "territory_id": 7963,
    "value_mwh": 12986051.8845494
  },
  {
    "base_group": null,
    "category_code": "cons_domestic",
    "domain": "consumption",
    "mun_cod": null,
    "name": "Sondrio",
    "prov_cod": 14,
    "reg_cod": 3,
    "territory_id": 7964,
    "value_mwh": 12445355.9881988
  },
  {
    "base_group": null,
    "category_code": "cons_domestic",
    "domain": "consumption",
    "mun_cod": null,
    "name": "Rovigo",
    "prov_cod": 29,
    "reg_cod": 5,
    "territory_id": 7965,
    "value_mwh": 17639760.588573
  },
  {
    "base_group": null,
    "category_code": "cons_domestic",
    "domain": "consumption",
    "mun_cod": null,
    "name": "Padova",
    "prov_cod": 28,
    "reg_cod": 5,
    "territory_id": 7966,
    "value_mwh": 70804417.724481
  },
  {
    "base_group": null,
    "category_code": "cons_domestic",
    "domain": "consumption",
    "mun_cod": null,
    "name": "Massa Carrara",
    "prov_cod": 45,
    "reg_cod": 9,
    "territory_id": 7967,
    "value_mwh": 12649862.740076
  },
  {
    "base_group": null,
    "category_code": "cons_domestic",
    "domain": "consumption",
    "mun_cod": null,
    "name": "Varese",
    "prov_cod": 12,
    "reg_cod": 3,
    "territory_id": 7968,
    "value_mwh": 63168270.7391965
  },
  {
    "base_group": null,
    "category_code": "cons_domestic",
    "domain": "consumption",
    "mun_cod": null,
    "name": "Grosseto",
    "prov_cod": 53,
    "reg_cod": 9,
    "territory_id": 7969,
    "value_mwh": 17829599.498062
  },
  {
    "base_group": null,
    "category_code": "cons_domestic",
    "domain": "consumption",
    "mun_cod": null,
    "name": "Brescia",
    "prov_cod": 17,
    "reg_cod": 3,
    "territory_id": 7970,
    "value_mwh": 94920217.4715575
  },
  {
    "base_group": null,
    "category_code": "cons_domestic",
    "domain": "consumption",
    "mun_cod": null,
    "name": "Perugia",
    "prov_cod": 54,
    "reg_cod": 10,
    "territory_id": 7971,
    "value_mwh": 44952077.9502925
  },
  {
    "base_group": null,
    "category_code": "cons_domestic",
    "domain": "consumption",
    "mun_cod": null,
    "name": "Cuneo",
    "prov_cod": 4,
    "reg_cod": 1,
    "territory_id": 7972,
    "value_mwh": 38975716.8066375
  },
  {
    "base_group": null,
    "category_code": "cons_domestic",
    "domain": "consumption",
    "mun_cod": null,
    "name": "Ravenna",
    "prov_cod": 39,
    "reg_cod": 8,
    "territory_id": 7973,
    "value_mwh": 28593258.21203
  },
  {
    "base_group": null,
    "category_code": "cons_domestic",
    "domain": "consumption",
    "mun_cod": null,
    "name": "Ferrara",
    "prov_cod": 38,
    "reg_cod": 8,
    "territory_id": 7974,
    "value_mwh": 26370425.57433
  },
  {
    "base_group": null,
    "category_code": "cons_domestic",
    "domain": "consumption",
    "mun_cod": null,
    "name": "Barletta-Andria-Trani",
    "prov_cod": 110,
    "reg_cod": 16,
    "territory_id": 7975,
    "value_mwh": 24187369.77036
  },
  {
    "base_group": null,
    "category_code": "cons_domestic",
    "domain": "consumption",
    "mun_cod": null,
    "name": "Verbano-Cusio-Ossola",
    "prov_cod": 103,
    "reg_cod": 1,
    "territory_id": 7976,
    "value_mwh": 10598278.7434754
  },
  {
    "base_group": null,
    "category_code": "cons_domestic",
    "domain": "consumption",
    "mun_cod": null,
    "name": "Mantova",
    "prov_cod": 20,
    "reg_cod": 3,
    "territory_id": 7977,
    "value_mwh": 30717769.616592
  },
  {
    "base_group": null,
    "category_code": "cons_domestic",
    "domain": "consumption",
    "mun_cod": null,
    "name": "Bergamo",
    "prov_cod": 16,
    "reg_cod": 3,
    "territory_id": 7978,
    "value_mwh": 76100899.7203746
  },
  {
    "base_group": null,
    "category_code": "cons_domestic",
    "domain": "consumption",
    "mun_cod": null,
    "name": "Sud Sardegna",
    "prov_cod": 111,
    "reg_cod": 20,
    "territory_id": 7979,
    "value_mwh": 39359198.751246
  },
  {
    "base_group": null,
    "category_code": "cons_domestic",
    "domain": "consumption",
    "mun_cod": null,
    "name": "Piacenza",
    "prov_cod": 33,
    "reg_cod": 8,
    "territory_id": 7980,
    "value_mwh": 21274977.425201
  },
  {
    "base_group": null,
    "category_code": "cons_domestic",
    "domain": "consumption",
    "mun_cod": null,
    "name": "Foggia",
    "prov_cod": 71,
    "reg_cod": 16,
    "territory_id": 7981,
    "value_mwh": 35355389.8125125
  },
  {
    "base_group": null,
    "category_code": "cons_domestic",
    "domain": "consumption",
    "mun_cod": null,
    "name": "Firenze",
    "prov_cod": 48,
    "reg_cod": 9,
    "territory_id": 7982,
    "value_mwh": 68829099.902633
  },
  {
    "base_group": null,
    "category_code": "cons_domestic",
    "domain": "consumption",
    "mun_cod": null,
    "name": "Genova",
    "prov_cod": 10,
    "reg_cod": 7,
    "territory_id": 7983,
    "value_mwh": 54363065.9431359
  },
  {
    "base_group": null,
    "category_code": "cons_domestic",
    "domain": "consumption",
    "mun_cod": null,
    "name": "Catania",
    "prov_cod": 87,
    "reg_cod": 19,
    "territory_id": 7984,
    "value_mwh": 78456669.076019
  },
  {
    "base_group": null,
    "category_code": "cons_domestic",
    "domain": "consumption",
    "mun_cod": null,
    "name": "Milano",
    "prov_cod": 15,
    "reg_cod": 3,
    "territory_id": 7985,
    "value_mwh": 245935849.941471
  },
  {
    "base_group": null,
    "category_code": "cons_domestic",
    "domain": "consumption",
    "mun_cod": null,
    "name": "Cosenza",
    "prov_cod": 78,
    "reg_cod": 18,
    "territory_id": 7986,
    "value_mwh": 46845324.5376555
  },
  {
    "base_group": null,
    "category_code": "cons_domestic",
    "domain": "consumption",
    "mun_cod": null,
    "name": "Taranto",
    "prov_cod": 73,
    "reg_cod": 16,
    "territory_id": 7987,
    "value_mwh": 40458956.082041
  },
  {
    "base_group": null,
    "category_code": "cons_domestic",
    "domain": "consumption",
    "mun_cod": null,
    "name": "Teramo",
    "prov_cod": 67,
    "reg_cod": 13,
    "territory_id": 7988,
    "value_mwh": 19866017.008151
  },
  {
    "base_group": null,
    "category_code": "cons_domestic",
    "domain": "consumption",
    "mun_cod": null,
    "name": "Belluno",
    "prov_cod": 25,
    "reg_cod": 5,
    "territory_id": 7989,
    "value_mwh": 13851320.4503835
  },
  {
    "base_group": null,
    "category_code": "cons_domestic",
    "domain": "consumption",
    "mun_cod": null,
    "name": "Latina",
    "prov_cod": 59,
    "reg_cod": 12,
    "territory_id": 7990,
    "value_mwh": 41754800.514321
  },
  {
    "base_group": null,
    "category_code": "cons_domestic",
    "domain": "consumption",
    "mun_cod": null,
    "name": "Livorno",
    "prov_cod": 49,
    "reg_cod": 9,
    "territory_id": 7991,
    "value_mwh": 23940764.786777
  },
  {
    "base_group": null,
    "category_code": "cons_domestic",
    "domain": "consumption",
    "mun_cod": null,
    "name": "Vicenza",
    "prov_cod": 24,
    "reg_cod": 5,
    "territory_id": 7992,
    "value_mwh": 61759558.131743
  },
  {
    "base_group": null,
    "category_code": "cons_domestic",
    "domain": "consumption",
    "mun_cod": null,
    "name": "Novara",
    "prov_cod": 3,
    "reg_cod": 1,
    "territory_id": 7993,
    "value_mwh": 25854704.848379
  },
  {
    "base_group": null,
    "category_code": "cons_domestic",
    "domain": "consumption",
    "mun_cod": null,
    "name": "Agrigento",
    "prov_cod": 84,
    "reg_cod": 19,
    "territory_id": 7994,
    "value_mwh": 31511392.367517
  },
  {
    "base_group": null,
    "category_code": "cons_domestic",
    "domain": "consumption",
    "mun_cod": null,
    "name": "Gorizia",
    "prov_cod": 31,
    "reg_cod": 6,
    "territory_id": 7995,
    "value_mwh": 9296874.168006
  },
  {
    "base_group": null,
    "category_code": "cons_domestic",
    "domain": "consumption",
    "mun_cod": null,
    "name": "Matera",
    "prov_cod": 77,
    "reg_cod": 17,
    "territory_id": 7996,
    "value_mwh": 11998605.91572
  },
  {
    "base_group": null,
    "category_code": "cons_domestic",
    "domain": "consumption",
    "mun_cod": null,
    "name": "La Spezia",
    "prov_cod": 11,
    "reg_cod": 7,
    "territory_id": 7997,
    "value_mwh": 14806780.959365
  },
  {
    "base_group": null,
    "category_code": "cons_domestic",
    "domain": "consumption",
    "mun_cod": null,
    "name": "Udine",
    "prov_cod": 30,
    "reg_cod": 6,
    "territory_id": 7998,
    "value_mwh": 39214572.0859406
  },
  {
    "base_group": null,
    "category_code": "cons_domestic",
    "domain": "consumption",
    "mun_cod": null,
    "name": "Parma",
    "prov_cod": 34,
    "reg_cod": 8,
    "territory_id": 7999,
    "value_mwh": 33716362.050754
  },
  {
    "base_group": null,
    "category_code": "cons_domestic",
    "domain": "consumption",
    "mun_cod": null,
    "name": "Reggio nell'Emilia",
    "prov_cod": 35,
    "reg_cod": 8,
    "territory_id": 8000,
    "value_mwh": 38134405.051134
  },
  {
    "base_group": null,
    "category_code": "cons_domestic",
    "domain": "consumption",
    "mun_cod": null,
    "name": "Trapani",
    "prov_cod": 81,
    "reg_cod": 19,
    "territory_id": 8001,
    "value_mwh": 36607311.681815
  },
  {
    "base_group": null,
    "category_code": "cons_domestic",
    "domain": "consumption",
    "mun_cod": null,
    "name": "Isernia",
    "prov_cod": 94,
    "reg_cod": 14,
    "territory_id": 8002,
    "value_mwh": 4662521.9713617
  },
  {
    "base_group": null,
    "category_code": "cons_domestic",
    "domain": "consumption",
    "mun_cod": null,
    "name": "Ragusa",
    "prov_cod": 88,
    "reg_cod": 19,
    "territory_id": 8003,
    "value_mwh": 26633252.67247
  },
  {
    "base_group": null,
    "category_code": "cons_domestic",
    "domain": "consumption",
    "mun_cod": null,
    "name": "Trento",
    "prov_cod": 22,
    "reg_cod": 4,
    "territory_id": 8004,
    "value_mwh": 36795768.443388
  },
  {
    "base_group": null,
    "category_code": "cons_domestic",
    "domain": "consumption",
    "mun_cod": null,
    "name": "Vibo Valentia",
    "prov_cod": 102,
    "reg_cod": 18,
    "territory_id": 8005,
    "value_mwh": 10060073.713947
  },
  {
    "base_group": null,
    "category_code": "cons_domestic",
    "domain": "consumption",
    "mun_cod": null,
    "name": "Enna",
    "prov_cod": 86,
    "reg_cod": 19,
    "territory_id": 8006,
    "value_mwh": 10192520.368756
  },
  {
    "base_group": null,
    "category_code": "cons_domestic",
    "domain": "consumption",
    "mun_cod": null,
    "name": "Lucca",
    "prov_cod": 46,
    "reg_cod": 9,
    "territory_id": 8007,
    "value_mwh": 30523820.508633
  },
  {
    "base_group": null,
    "category_code": "cons_domestic",
    "domain": "consumption",
    "mun_cod": null,
    "name": "Aosta",
    "prov_cod": 7,
    "reg_cod": 2,
    "territory_id": 8008,
    "value_mwh": 10020146.4377479
  }
]